celium_cli/__init__.py
celium_cli/cli.py
celium_cli/src/cli_manager.py
celium_cli/src/config.py
celium_cli/src/const.py
celium_cli/src/decorator.py
celium_cli/src/styles.py
celium_cli/src/utils.py
celium_cli/src/version.py
celium_cli/src/apps/__init__.py
celium_cli/src/apps/config.py
celium_cli/src/apps/exceptions.py
celium_cli/src/apps/pay.py
celium_cli/src/apps/pod.py
celium_cli/src/apps/ssh.py
celium_cli/src/apps/template.py
celium_cli/src/apps/theme.py
celium_cli/src/services/__init__.py
celium_cli/src/services/api.py
celium_cli/src/services/docker.py
celium_cli/src/services/docker_credential.py
celium_cli/src/services/executor.py
celium_cli/src/services/tao.py
celium_cli/src/services/template.py
celium_cli/src/services/user.py
celium_cli/src/services/validator.py
celium_cli/src/services/wallet.py
celium_cli-0.2.1.dist-info/licenses/LICENSE
celium_cli-0.2.1.dist-info/METADATA
celium_cli-0.2.1.dist-info/WHEEL
celium_cli-0.2.1.dist-info/entry_points.txt
celium_cli-0.2.1.dist-info/top_level.txt
celium_cli-0.2.1.dist-info/RECORD
