Metadata-Version: 2.4
Name: celium-cli
Version: 0.2.1
Summary: A custom CLI tool for Celium. Celium CLI provides tools for interacting with the Celium ecosystem from the command line.
Author-email: Celium <support@celium.ai>
License-Expression: MIT
Project-URL: homepage, https://github.com/Datura-ai/celium-cli
Project-URL: repository, https://github.com/Datura-ai/celium-cli
Project-URL: issues, https://github.com/Datura-ai/celium-cli/issues
Classifier: Development Status :: 4 - Beta
Classifier: Intended Audience :: Developers
Classifier: Programming Language :: Python :: 3
Classifier: Programming Language :: Python :: 3.9
Classifier: Programming Language :: Python :: 3.10
Classifier: Programming Language :: Python :: 3.11
Classifier: Programming Language :: Python :: 3.12
Classifier: Operating System :: OS Independent
Requires-Python: >=3.9
License-File: LICENSE
Requires-Dist: typer<0.16,>=0.12
Requires-Dist: rich<15.0,>=13.7
Requires-Dist: pycryptodome<4.0.0,>=3.0.0
Requires-Dist: PyYAML~=6.0.1
Requires-Dist: aiohttp~=3.10.2
Requires-Dist: backoff~=2.2.1
Requires-Dist: GitPython>=3.0.0
Requires-Dist: async-substrate-interface>=1.1.0
Requires-Dist: scalecodec==1.2.11
Requires-Dist: plotly>=6.0.0
Requires-Dist: plotille>=5.0.0
Requires-Dist: fuzzywuzzy~=0.18.0
Requires-Dist: python-Levenshtein
Requires-Dist: netaddr~=1.3.0
Requires-Dist: Jinja2
Requires-Dist: pywry>=0.6.2
Requires-Dist: async-property==0.2.2
Requires-Dist: bittensor-cli>=8.4.3
Requires-Dist: paramiko==3.5.0
Provides-Extra: dev
Requires-Dist: pytest; extra == "dev"
Requires-Dist: black; extra == "dev"
Requires-Dist: wheel; extra == "dev"
Dynamic: license-file
